[
  {
    "name": "Process Start",
    "start": 1602235315831,
    "end": 1602235316655,
    "duration": 824,
    "pid": 8060,
    "index": 0
  },
  {
    "name": "Application Start",
    "start": 1602235316656,
    "end": 1602235317224,
    "duration": 568,
    "pid": 8060,
    "index": 1
  },
  {
    "name": "Load Plugin",
    "start": 1602235316660,
    "end": 1602235316671,
    "duration": 11,
    "pid": 8060,
    "index": 2
  },
  {
    "name": "Load Config",
    "start": 1602235316672,
    "end": 1602235316691,
    "duration": 19,
    "pid": 8060,
    "index": 3
  },
  {
    "name": "Require(0) config/config.default.js",
    "start": 1602235316672,
    "end": 1602235316672,
    "duration": 0,
    "pid": 8060,
    "index": 4
  },
  {
    "name": "Require(1) node_modules/egg-session/config/config.default.js",
    "start": 1602235316674,
    "end": 1602235316674,
    "duration": 0,
    "pid": 8060,
    "index": 5
  },
  {
    "name": "Require(2) node_modules/egg-security/config/config.default.js",
    "start": 1602235316675,
    "end": 1602235316676,
    "duration": 1,
    "pid": 8060,
    "index": 6
  },
  {
    "name": "Require(3) node_modules/egg-jsonp/config/config.default.js",
    "start": 1602235316677,
    "end": 1602235316677,
    "duration": 0,
    "pid": 8060,
    "index": 7
  },
  {
    "name": "Require(4) node_modules/egg-onerror/config/config.default.js",
    "start": 1602235316677,
    "end": 1602235316678,
    "duration": 1,
    "pid": 8060,
    "index": 8
  },
  {
    "name": "Require(5) node_modules/egg-i18n/config/config.default.js",
    "start": 1602235316678,
    "end": 1602235316678,
    "duration": 0,
    "pid": 8060,
    "index": 9
  },
  {
    "name": "Require(6) node_modules/egg-watcher/config/config.default.js",
    "start": 1602235316679,
    "end": 1602235316679,
    "duration": 0,
    "pid": 8060,
    "index": 10
  },
  {
    "name": "Require(7) node_modules/egg-schedule/config/config.default.js",
    "start": 1602235316679,
    "end": 1602235316680,
    "duration": 1,
    "pid": 8060,
    "index": 11
  },
  {
    "name": "Require(8) node_modules/egg-multipart/config/config.default.js",
    "start": 1602235316680,
    "end": 1602235316680,
    "duration": 0,
    "pid": 8060,
    "index": 12
  },
  {
    "name": "Require(9) node_modules/egg-development/config/config.default.js",
    "start": 1602235316681,
    "end": 1602235316681,
    "duration": 0,
    "pid": 8060,
    "index": 13
  },
  {
    "name": "Require(10) node_modules/egg-logrotator/config/config.default.js",
    "start": 1602235316682,
    "end": 1602235316682,
    "duration": 0,
    "pid": 8060,
    "index": 14
  },
  {
    "name": "Require(11) node_modules/egg-static/config/config.default.js",
    "start": 1602235316682,
    "end": 1602235316682,
    "duration": 0,
    "pid": 8060,
    "index": 15
  },
  {
    "name": "Require(12) node_modules/egg-view/config/config.default.js",
    "start": 1602235316683,
    "end": 1602235316683,
    "duration": 0,
    "pid": 8060,
    "index": 16
  },
  {
    "name": "Require(13) node_modules/egg-view-nunjucks/config/config.default.js",
    "start": 1602235316684,
    "end": 1602235316684,
    "duration": 0,
    "pid": 8060,
    "index": 17
  },
  {
    "name": "Require(14) node_modules/egg-mysql/config/config.default.js",
    "start": 1602235316684,
    "end": 1602235316685,
    "duration": 1,
    "pid": 8060,
    "index": 18
  },
  {
    "name": "Require(15) node_modules/egg/config/config.default.js",
    "start": 1602235316685,
    "end": 1602235316685,
    "duration": 0,
    "pid": 8060,
    "index": 19
  },
  {
    "name": "Require(16) config/config.default.js",
    "start": 1602235316687,
    "end": 1602235316687,
    "duration": 0,
    "pid": 8060,
    "index": 20
  },
  {
    "name": "Require(17) node_modules/egg-security/config/config.local.js",
    "start": 1602235316687,
    "end": 1602235316688,
    "duration": 1,
    "pid": 8060,
    "index": 21
  },
  {
    "name": "Require(18) node_modules/egg-watcher/config/config.local.js",
    "start": 1602235316688,
    "end": 1602235316688,
    "duration": 0,
    "pid": 8060,
    "index": 22
  },
  {
    "name": "Require(19) node_modules/egg-view/config/config.local.js",
    "start": 1602235316689,
    "end": 1602235316689,
    "duration": 0,
    "pid": 8060,
    "index": 23
  },
  {
    "name": "Require(20) node_modules/egg-view-nunjucks/config/config.local.js",
    "start": 1602235316690,
    "end": 1602235316690,
    "duration": 0,
    "pid": 8060,
    "index": 24
  },
  {
    "name": "Require(21) node_modules/egg/config/config.local.js",
    "start": 1602235316690,
    "end": 1602235316691,
    "duration": 1,
    "pid": 8060,
    "index": 25
  },
  {
    "name": "Load extend/application.js",
    "start": 1602235316692,
    "end": 1602235316721,
    "duration": 29,
    "pid": 8060,
    "index": 26
  },
  {
    "name": "Require(22) node_modules/egg-session/app/extend/application.js",
    "start": 1602235316692,
    "end": 1602235316693,
    "duration": 1,
    "pid": 8060,
    "index": 27
  },
  {
    "name": "Require(23) node_modules/egg-security/app/extend/application.js",
    "start": 1602235316693,
    "end": 1602235316694,
    "duration": 1,
    "pid": 8060,
    "index": 28
  },
  {
    "name": "Require(24) node_modules/egg-jsonp/app/extend/application.js",
    "start": 1602235316694,
    "end": 1602235316695,
    "duration": 1,
    "pid": 8060,
    "index": 29
  },
  {
    "name": "Require(25) node_modules/egg-logrotator/app/extend/application.js",
    "start": 1602235316696,
    "end": 1602235316697,
    "duration": 1,
    "pid": 8060,
    "index": 30
  },
  {
    "name": "Require(26) node_modules/egg-view/app/extend/application.js",
    "start": 1602235316697,
    "end": 1602235316698,
    "duration": 1,
    "pid": 8060,
    "index": 31
  },
  {
    "name": "Require(27) node_modules/egg-view-nunjucks/app/extend/application.js",
    "start": 1602235316698,
    "end": 1602235316720,
    "duration": 22,
    "pid": 8060,
    "index": 32
  },
  {
    "name": "Load extend/request.js",
    "start": 1602235316721,
    "end": 1602235316729,
    "duration": 8,
    "pid": 8060,
    "index": 33
  },
  {
    "name": "Require(28) node_modules/egg/app/extend/request.js",
    "start": 1602235316727,
    "end": 1602235316728,
    "duration": 1,
    "pid": 8060,
    "index": 34
  },
  {
    "name": "Load extend/response.js",
    "start": 1602235316729,
    "end": 1602235316734,
    "duration": 5,
    "pid": 8060,
    "index": 35
  },
  {
    "name": "Require(29) node_modules/egg/app/extend/response.js",
    "start": 1602235316731,
    "end": 1602235316732,
    "duration": 1,
    "pid": 8060,
    "index": 36
  },
  {
    "name": "Load extend/context.js",
    "start": 1602235316734,
    "end": 1602235316801,
    "duration": 67,
    "pid": 8060,
    "index": 37
  },
  {
    "name": "Require(30) node_modules/egg-security/app/extend/context.js",
    "start": 1602235316734,
    "end": 1602235316742,
    "duration": 8,
    "pid": 8060,
    "index": 38
  },
  {
    "name": "Require(31) node_modules/egg-jsonp/app/extend/context.js",
    "start": 1602235316742,
    "end": 1602235316743,
    "duration": 1,
    "pid": 8060,
    "index": 39
  },
  {
    "name": "Require(32) node_modules/egg-i18n/app/extend/context.js",
    "start": 1602235316744,
    "end": 1602235316744,
    "duration": 0,
    "pid": 8060,
    "index": 40
  },
  {
    "name": "Require(33) node_modules/egg-multipart/app/extend/context.js",
    "start": 1602235316744,
    "end": 1602235316796,
    "duration": 52,
    "pid": 8060,
    "index": 41
  },
  {
    "name": "Require(34) node_modules/egg-view/app/extend/context.js",
    "start": 1602235316797,
    "end": 1602235316798,
    "duration": 1,
    "pid": 8060,
    "index": 42
  },
  {
    "name": "Require(35) node_modules/egg/app/extend/context.js",
    "start": 1602235316798,
    "end": 1602235316799,
    "duration": 1,
    "pid": 8060,
    "index": 43
  },
  {
    "name": "Load extend/helper.js",
    "start": 1602235316801,
    "end": 1602235316826,
    "duration": 25,
    "pid": 8060,
    "index": 44
  },
  {
    "name": "Require(36) node_modules/egg-security/app/extend/helper.js",
    "start": 1602235316802,
    "end": 1602235316821,
    "duration": 19,
    "pid": 8060,
    "index": 45
  },
  {
    "name": "Require(37) node_modules/egg/app/extend/helper.js",
    "start": 1602235316823,
    "end": 1602235316823,
    "duration": 0,
    "pid": 8060,
    "index": 46
  },
  {
    "name": "Load app.js",
    "start": 1602235316826,
    "end": 1602235316870,
    "duration": 44,
    "pid": 8060,
    "index": 47
  },
  {
    "name": "Require(38) node_modules/egg-session/app.js",
    "start": 1602235316827,
    "end": 1602235316827,
    "duration": 0,
    "pid": 8060,
    "index": 48
  },
  {
    "name": "Require(39) node_modules/egg-security/app.js",
    "start": 1602235316827,
    "end": 1602235316828,
    "duration": 1,
    "pid": 8060,
    "index": 49
  },
  {
    "name": "Require(40) node_modules/egg-onerror/app.js",
    "start": 1602235316828,
    "end": 1602235316836,
    "duration": 8,
    "pid": 8060,
    "index": 50
  },
  {
    "name": "Require(41) node_modules/egg-i18n/app.js",
    "start": 1602235316837,
    "end": 1602235316850,
    "duration": 13,
    "pid": 8060,
    "index": 51
  },
  {
    "name": "Require(42) node_modules/egg-watcher/app.js",
    "start": 1602235316850,
    "end": 1602235316853,
    "duration": 3,
    "pid": 8060,
    "index": 52
  },
  {
    "name": "Require(43) node_modules/egg-schedule/app.js",
    "start": 1602235316853,
    "end": 1602235316854,
    "duration": 1,
    "pid": 8060,
    "index": 53
  },
  {
    "name": "Require(44) node_modules/egg-multipart/app.js",
    "start": 1602235316854,
    "end": 1602235316854,
    "duration": 0,
    "pid": 8060,
    "index": 54
  },
  {
    "name": "Require(45) node_modules/egg-development/app.js",
    "start": 1602235316855,
    "end": 1602235316855,
    "duration": 0,
    "pid": 8060,
    "index": 55
  },
  {
    "name": "Require(46) node_modules/egg-logrotator/app.js",
    "start": 1602235316855,
    "end": 1602235316855,
    "duration": 0,
    "pid": 8060,
    "index": 56
  },
  {
    "name": "Require(47) node_modules/egg-static/app.js",
    "start": 1602235316856,
    "end": 1602235316856,
    "duration": 0,
    "pid": 8060,
    "index": 57
  },
  {
    "name": "Require(48) node_modules/egg-view-nunjucks/app.js",
    "start": 1602235316856,
    "end": 1602235316856,
    "duration": 0,
    "pid": 8060,
    "index": 58
  },
  {
    "name": "Require(49) node_modules/egg-mysql/app.js",
    "start": 1602235316857,
    "end": 1602235316869,
    "duration": 12,
    "pid": 8060,
    "index": 59
  },
  {
    "name": "Before Start in node_modules/egg-watcher/lib/init.js:15:14",
    "start": 1602235316878,
    "end": 1602235317189,
    "duration": 311,
    "pid": 8060,
    "index": 60
  },
  {
    "name": "Before Start in node_modules/egg-mysql/lib/mysql.js:20:7",
    "start": 1602235316980,
    "end": 1602235317223,
    "duration": 243,
    "pid": 8060,
    "index": 61
  },
  {
    "name": "Load Service",
    "start": 1602235316980,
    "end": 1602235316993,
    "duration": 13,
    "pid": 8060,
    "index": 62
  },
  {
    "name": "Load \"service\" to Context",
    "start": 1602235316980,
    "end": 1602235316993,
    "duration": 13,
    "pid": 8060,
    "index": 63
  },
  {
    "name": "Load Middleware",
    "start": 1602235316993,
    "end": 1602235317154,
    "duration": 161,
    "pid": 8060,
    "index": 64
  },
  {
    "name": "Load \"middlewares\" to Application",
    "start": 1602235316993,
    "end": 1602235317136,
    "duration": 143,
    "pid": 8060,
    "index": 65
  },
  {
    "name": "Load Controller",
    "start": 1602235317154,
    "end": 1602235317163,
    "duration": 9,
    "pid": 8060,
    "index": 66
  },
  {
    "name": "Load \"controller\" to Application",
    "start": 1602235317154,
    "end": 1602235317163,
    "duration": 9,
    "pid": 8060,
    "index": 67
  },
  {
    "name": "Load Router",
    "start": 1602235317163,
    "end": 1602235317166,
    "duration": 3,
    "pid": 8060,
    "index": 68
  },
  {
    "name": "Require(50) app/router.js",
    "start": 1602235317164,
    "end": 1602235317164,
    "duration": 0,
    "pid": 8060,
    "index": 69
  },
  {
    "name": "Before Start in node_modules/egg-core/lib/egg.js:303:10",
    "start": 1602235317165,
    "end": 1602235317181,
    "duration": 16,
    "pid": 8060,
    "index": 70
  }
]